mailtrail/__init__.py
mailtrail/__main__.py
mailtrail/config.py
mailtrail/graphconnector.py
mailtrail/mailtrail.py
mailtrail/utils/__init__.py
mailtrail/utils/version.py
mailtrail-0.0.1.dist-info/LICENSE.md
mailtrail-0.0.1.dist-info/METADATA
mailtrail-0.0.1.dist-info/WHEEL
mailtrail-0.0.1.dist-info/entry_points.txt
mailtrail-0.0.1.dist-info/top_level.txt
mailtrail-0.0.1.dist-info/RECORD
