Metadata-Version: 2.1
Name: mailtrail
Version: 0.0.1
Summary: Retrieve and forward Exchange or Office 365 mail messages to logging infrastructure.
Home-page: https://github.com/MSAdministrator/mailtrail
Author: MSAdministrator
Author-email: rickardja@live.com
License: MIT
Keywords: carcass
Platform: UNKNOWN
Requires-Python: >=2.6, !=3.0.*, !=3.1.*, !=3.2.*, <4
